{
"type": "FeatureCollection",
"name": "coba",
"crs": { "type": "name", "properties": { "name": "urn:ogc:def:crs:OGC:1.3:CRS84" } },
"features": [
{ "type": "Feature", "properties": { "No": true, "Nama": "TOKO MAMA RIMBA", "X": 120.464893, "Y": -6.1239262 }, "geometry": { "type": "Point", "coordinates": [ 120.464893, -6.1239262 ] } }
]
}
